{
    "version": "1.0.0",
    "summary": "flight path sun graph",
    "repository": "https://github.com/karldray/sunpath.git",
    "license": "BSD3",
    "source-directories": [
        "src"
    ],
    "exposed-modules": [],
    "dependencies": {
        "circuithub/elm-number-format": "1.0.1 <= v < 2.0.0",
        "elm-lang/core": "2.0.1 <= v < 3.0.0",
        "evancz/elm-html": "3.0.0 <= v < 4.0.0",
        "evancz/elm-http": "1.0.0 <= v < 2.0.0",
        "johnpmayer/elm-linear-algebra": "2.0.1 <= v < 3.0.0",
        "johnpmayer/elm-webgl": "3.0.0 <= v < 4.0.0",
        "karldray/elm-ref": "3.3.0 <= v < 4.0.0"
    },
    "elm-version": "0.15.0 <= v < 0.16.0"
}